chat/__init__.py
ChatPackage-1.1.dist-info/LICENSE
ChatPackage-1.1.dist-info/METADATA
ChatPackage-1.1.dist-info/WHEEL
ChatPackage-1.1.dist-info/top_level.txt
ChatPackage-1.1.dist-info/RECORD
