Metadata-Version: 2.1
Name: ChatPackage
Version: 1.1
Summary: Testing Chat Package
Home-page: https://github.com/riturajpandey/ChatPackage
Author: Ashwini Bokade
Author-email: ashwini_bokade@yahoo.com
License: UNKNOWN
Platform: UNKNOWN
Classifier: Programming Language :: Python :: 3.7
Classifier: License :: OSI Approved :: GNU Lesser General Public License v3 (LGPLv3)
Classifier: Operating System :: OS Independent
